<annotation>
  <filename>vehicle_public_roads_avenue_00094_train_p_day_20210416_1199.jpg</filename>
  <size>
    <width>4096</width>
    <height>2160</height>
    <depth>3</depth>
  </size>
  <object>
    <name>motorbike</name>
    <bndbox>
      <xmin>850</xmin>
      <ymin>524</ymin>
      <xmax>1000</xmax>
      <ymax>648</ymax>
    </bndbox>
  </object>
  <object>
    <name>motorbike</name>
    <bndbox>
      <xmin>2135</xmin>
      <ymin>1517</ymin>
      <xmax>2419</xmax>
      <ymax>2092</ymax>
    </bndbox>
  </object>
  <object>
    <name>motorbike</name>
    <bndbox>
      <xmin>1413</xmin>
      <ymin>702</ymin>
      <xmax>1679</xmax>
      <ymax>897</ymax>
    </bndbox>
  </object>
  <object>
    <name>car</name>
    <bndbox>
      <xmin>2172</xmin>
      <ymin>505</ymin>
      <xmax>3848</xmax>
      <ymax>1344</ymax>
    </bndbox>
  </object>
  <object>
    <name>car</name>
    <bndbox>
      <xmin>285</xmin>
      <ymin>494</ymin>
      <xmax>887</xmax>
      <ymax>860</ymax>
    </bndbox>
  </object>
  <object>
    <name>car</name>
    <bndbox>
      <xmin>8</xmin>
      <ymin>355</ymin>
      <xmax>486</xmax>
      <ymax>1150</ymax>
    </bndbox>
  </object>
</annotation>
